odoo8_addon_product_variant_weight-8.0.1.0.0.99.dev24-py3.8-nspkg.pth
odoo_addons/product_variant_weight/README.rst
odoo_addons/product_variant_weight/__init__.py
odoo_addons/product_variant_weight/__openerp__.py
odoo_addons/product_variant_weight/hooks.py
odoo_addons/product_variant_weight/i18n/ca.po
odoo_addons/product_variant_weight/i18n/de.po
odoo_addons/product_variant_weight/i18n/el_GR.po
odoo_addons/product_variant_weight/i18n/es.po
odoo_addons/product_variant_weight/i18n/es_ES.po
odoo_addons/product_variant_weight/i18n/es_MX.po
odoo_addons/product_variant_weight/i18n/eu.po
odoo_addons/product_variant_weight/i18n/fi.po
odoo_addons/product_variant_weight/i18n/fr.po
odoo_addons/product_variant_weight/i18n/fr_CH.po
odoo_addons/product_variant_weight/i18n/fr_FR.po
odoo_addons/product_variant_weight/i18n/gl.po
odoo_addons/product_variant_weight/i18n/hr.po
odoo_addons/product_variant_weight/i18n/hr_HR.po
odoo_addons/product_variant_weight/i18n/it.po
odoo_addons/product_variant_weight/i18n/nl.po
odoo_addons/product_variant_weight/i18n/nl_NL.po
odoo_addons/product_variant_weight/i18n/product_variant_weight.pot
odoo_addons/product_variant_weight/i18n/pt.po
odoo_addons/product_variant_weight/i18n/pt_BR.po
odoo_addons/product_variant_weight/i18n/ro.po
odoo_addons/product_variant_weight/i18n/ru.po
odoo_addons/product_variant_weight/i18n/sk.po
odoo_addons/product_variant_weight/i18n/sl.po
odoo_addons/product_variant_weight/i18n/tr.po
odoo_addons/product_variant_weight/i18n/tr_TR.po
odoo_addons/product_variant_weight/i18n/vi_VN.po
odoo_addons/product_variant_weight/i18n/zh_CN.po
odoo_addons/product_variant_weight/models/__init__.py
odoo_addons/product_variant_weight/models/product.py
odoo_addons/product_variant_weight/static/description/icon.png
odoo_addons/product_variant_weight/tests/__init__.py
odoo_addons/product_variant_weight/tests/test_product_variant_weight.py
odoo8_addon_product_variant_weight-8.0.1.0.0.99.dev24.dist-info/METADATA
odoo8_addon_product_variant_weight-8.0.1.0.0.99.dev24.dist-info/WHEEL
odoo8_addon_product_variant_weight-8.0.1.0.0.99.dev24.dist-info/namespace_packages.txt
odoo8_addon_product_variant_weight-8.0.1.0.0.99.dev24.dist-info/top_level.txt
odoo8_addon_product_variant_weight-8.0.1.0.0.99.dev24.dist-info/RECORD
